airflow_common_operators/__init__.py
airflow_common_operators/airflow/__init__.py
airflow_common_operators/airflow/operators.py
airflow_common_operators/airflow/topology.py
airflow_common_operators/infra/__init__.py
airflow_common_operators/infra/commands.py
airflow_common_operators/infra/task.py
airflow_common_operators/library/__init__.py
airflow_common_operators/library/model.py
airflow_common_operators/library/task.py
airflow_common_operators/tests/test_git.py
airflow_common_operators/tests/test_helpers.py
airflow_common_operators/tests/test_journalctl.py
airflow_common_operators/tests/test_library.py
airflow_common_operators/tests/config/config.yaml
airflow_common_operators/tests/config/extensions/libraries.yaml
airflow_common_operators-0.7.5.dist-info/METADATA
airflow_common_operators-0.7.5.dist-info/WHEEL
airflow_common_operators-0.7.5.dist-info/licenses/LICENSE
airflow_common_operators-0.7.5.dist-info/RECORD
